bitwardentools/__init__.py
bitwardentools/client.py
bitwardentools/common.py
bitwardentools/create_and_notify.py
bitwardentools/crypto.py
bitwardentools/delete_user.py
bitwardentools/disable_user.py
bitwardentools/vaultier/__init__.py
bitwardentools/vaultier/create_users.py
bitwardentools/vaultier/export.py
bitwardentools/vaultier/import_structure.py
bitwardentools/vaultier/invite.py
bitwardentools/vaultier/notify.py
bitwardentools/vaultier/sync_secrets.py
bitwardentools/vaultier/wipe.py
bitwardentools/vaultier/wipe_users.py
tests/__init__.py
tests/test_client.py
bitwardentools-2.0.1.dist-info/LICENSE.txt
bitwardentools-2.0.1.dist-info/METADATA
bitwardentools-2.0.1.dist-info/WHEEL
bitwardentools-2.0.1.dist-info/namespace_packages.txt
bitwardentools-2.0.1.dist-info/top_level.txt
bitwardentools-2.0.1.dist-info/RECORD
