Metadata-Version: 2.2
Name: bitwardentools
Version: 2.0.1
Summary: bitwardentools
Home-page: https://github.com/corpusops/bitwardentools
Author: kiorky
Author-email: kiorky@cryptelium.net
License: GPL
Classifier: Programming Language :: Python
Classifier: Topic :: Software Development
License-File: LICENSE.txt
Requires-Dist: packaging
Requires-Dist: setuptools
Requires-Dist: click
Requires-Dist: hkdf
Requires-Dist: pycryptodome
Requires-Dist: pyjwt[crypto]
Requires-Dist: requests>=2.13.0
Dynamic: author
Dynamic: author-email
Dynamic: classifier
Dynamic: description
Dynamic: description-content-type
Dynamic: home-page
Dynamic: keywords
Dynamic: license
Dynamic: requires-dist
Dynamic: summary
